pelican/plugins/syntax_highlighting/__init__.py
pelican/plugins/syntax_highlighting/markdown_extension.py
pelican/plugins/syntax_highlighting/settings.py
pelican/plugins/syntax_highlighting/syntax_highlighting.py
pelican/plugins/syntax_highlighting/test_syntax_highlighting.py
pelican_syntax_highlighting-0.4.2.dist-info/METADATA
pelican_syntax_highlighting-0.4.2.dist-info/WHEEL
pelican_syntax_highlighting-0.4.2.dist-info/RECORD
